LICENSE
MANIFEST.in
README.md
setup.cfg
setup.py
django_boot_rhazes.egg-info/PKG-INFO
django_boot_rhazes.egg-info/SOURCES.txt
django_boot_rhazes.egg-info/dependency_links.txt
django_boot_rhazes.egg-info/top_level.txt
rhazes/__init__.py
rhazes/bean_builder.py
rhazes/context.py
rhazes/decorator.py
rhazes/dependency.py
rhazes/exceptions.py
rhazes/protocol.py
rhazes/scanner.py
rhazes/scope.py
rhazes/utils.py
rhazes/collections/__init__.py
rhazes/collections/stack.py
rhazes/test/__init__.py
rhazes/test/context.py