Metadata-Version: 2.1
Name: django-boot-rhazes
Version: 1.2.1
Summary: A Django DI manager
Home-page: https://github.com/django-boot/Rhazes
Author: Django Boot
Author-email: djangoboot@proton.me
Classifier: Environment :: Web Environment
Classifier: Intended Audience :: Developers
Classifier: Operating System :: OS Independent
Classifier: Programming Language :: Python
Classifier: Programming Language :: Python :: 3
Classifier: Programming Language :: Python :: 3 :: Only
Classifier: Programming Language :: Python :: 3.6
Classifier: Programming Language :: Python :: 3.7
Classifier: Programming Language :: Python :: 3.8
Classifier: Programming Language :: Python :: 3.9
Classifier: Topic :: Internet :: WWW/HTTP
Requires-Python: >=3.6
License-File: LICENSE
